my_adder1/__init__.py
myadder1-0.1.1.dist-info/METADATA
myadder1-0.1.1.dist-info/WHEEL
myadder1-0.1.1.dist-info/top_level.txt
myadder1-0.1.1.dist-info/RECORD
